gpr.v
module gpr(
    input clk,
    input wire we, //write enable
    input wire [2:0] rs1, rs2,ws, //read ,write 할 address
    input wire [15:0] wd,
    output wire [15:0] rd1,rd2     //rs1, rs2 주소에 있는 data
);
reg [15:0] gprarray [7:0];
assign rd1 = gprarray[rs1];
assign rd2 = gprarray[rs2];

integer i;
initial begin
    for(i=0;i<8;i++)
        gprarray[i] <= 16'b0;
end

always @(posedge clk) begin
    if(we) begin
        gprarray[ws] <= wd;
    end
end

endmodule

alucontrol.v
module alucontrol(
    input wire [1:0] alu_op,
    input wire [3:0] opcode,
    output reg [2:0] alu_cnt
);
always @ ({alu_op,opcode}) begin
    casex ({alu_op,opcode}) 
    6'b10xxxx: alu_cnt = 3'b000; //Load, Store (+) : offset이랑 더해야
    6'b01xxxx: alu_cnt = 3'b001; //beq, bne (-) : 비교하기위해 빼기
    6'b000010: alu_cnt = 3'b000; // +
    6'b000011: alu_cnt = 3'b001; // -
    6'b000100: alu_cnt = 3'b010; // ~
    6'b000101: alu_cnt = 3'b011; // <<
    6'b000110: alu_cnt = 3'b100; // >>
    6'b000111: alu_cnt = 3'b101; // &
    6'b001000: alu_cnt = 3'b110; // |
    6'b001001: alu_cnt = 3'b111; // slt
    default: alu_cnt = 3'b000;
    endcase
end
endmodule

alu.v
module alu(
    input wire [15:0] a,b,
    input wire [2:0] alu_cnt,

    output reg [15:0] result,
    output wire iszero
);

always @(*) begin
    case(alu_cnt)
    3'h0: result = a+b;
    3'h1: result = a-b;
    3'h2: result = ~a;
    3'h3: result = a<<b;
    3'h4: result = a>>b;
    3'h5: result = a & b;
    3'h6: result = a | b;
    3'h7:
        begin
            if (a<b) result = 16'b1;
            else result =16'b0;
        end
    default: result = a+b;
    endcase
end

assign iszero = (result==16'd0) ? 1'b1 : 1'b0;
endmodule

datamemory.v
module datamemory(
    input clk,
    input wire [15:0] mem_address, mem_write_data,
    input wire mem_write_enable, mem_read_enable,
    output [15:0] mem_read_data
);
reg [15:0] memory [7:0];
initial begin
  $readmemb("./memory/datamemory.txt",memory);
end

assign mem_read_data =(mem_write_enable)? memory[mem_address] : 1'b0; //for LW

always @ (posedge clk) begin
    if (mem_write_enable) begin
      memory[mem_address] <= mem_write_data;
    end
end
endmodule

instructionmemory.v
module instructionmemory(
    input wire [15:0] pc,
    output wire [15:0] instruction
);

reg [15:0] memory [5:0];
assign instruction = memory[{1'b0,pc[15:1]}];

initial begin
    $readmemb("./memory/instructionmemory.txt",memory);
end
endmodule

datapath.v
module datapath(
    input clk,
    output wire [3:0] opcode,
    input wire reg_dst, alu_src, mem_to_reg, reg_w, mem_r, mem_w, beq, bne, j,
    input wire [1:0] alu_op
); //chipcontrol의 반대

wire [15:0] instruction; //im
reg [15:0] pc;           //im
wire [15:0] mem_read_data; //dm

wire [15:0] alu_out;       
wire [2:0] alu_cnt;
wire [15:0] pc_plus2;
assign pc_plus2 = pc+ 16'd2;

assign opcode = instruction[15:12];
wire [15:0] rd1,rd2,wd; //gpr
wire [2:0] rs1, rs2, ws;
assign rs1 = instruction[11:9];
assign rs2 = instruction[8:6];
assign ws = reg_dst ? instruction[5:3] : instruction[8:6]; 
assign wd = mem_to_reg ? mem_read_data : alu_out;

wire [15:0] immext;
assign immext = {{10{instruction[5]}},instruction[5:0]}; //extend branch offset
wire [15:0] b;
assign b = alu_src? immext : rd2; //alu_src = 1이면 주소값을 가져가서 rd1과 더함(load,store 할 주소생성)

/// branch, jump를 위한 pc변경
wire [15:0] pc_branch, pc_jump, pc_next;
assign pc_branch = pc_plus2 + immext;
assign pc_jump = {pc_plus2[15:13], instruction[11:0],1'b0}; //다음pc 앞3개가져오고, word단위 맞추기 위해 뒤에 0붙임. 
wire iszero; //beq, bne 비교 결과값 (beq에서 조건맞으면 1, bne에서 조건맞으면 0)
assign pc_next = j? pc_jump : (((beq&iszero) | (bne&(~iszero))))? pc_branch : pc_plus2 ;

initial begin
  pc <= 16'b0;
end
always @ (posedge clk) begin
  pc <= pc_next;
end

instructionmemory im_connect(               //instructionmemory
    .pc(pc), .instruction(instruction)
);

datamemory dm_connect(                      //datamemory
    .clk(clk), .mem_address(alu_out), .mem_write_data(rd2),
    .mem_write_enable(mem_w), .mem_read_enable(mem_r),
    .mem_read_data(mem_read_data)
);

alu alu_connect(                            //alu
    .a(rd1), .b(b), .alu_cnt(alu_cnt), .result(alu_out), .iszero(iszero)
);

alucontrol alucontrol_connect(
    .alu_op(alu_op), .opcode(opcode), .alu_cnt(alu_cnt)
);

gpr gpr_connect(
    .clk(clk) ,.we(reg_w), .rs1(rs1), .rs2(rs2), .ws(ws), .rd1(rd1), .rd2(rd2), .wd(wd)
);

endmodule

chipcontrol.v
module chipcontrol(
    input wire [3:0] opcode,
    output reg reg_dst, alu_src, mem_to_reg, reg_w, mem_r, mem_w, beq, bne, j,
    output reg [1:0] alu_op
);

always @(*) begin
    case(opcode)
    4'd0: {reg_dst, alu_src, mem_to_reg, reg_w, mem_r, mem_w, beq, bne, alu_op[1:0], j}
    = 11'b01111000100;  //Load Word

    4'd1: {reg_dst, alu_src, mem_to_reg, reg_w, mem_r, mem_w, beq, bne, alu_op[1:0], j}
    = 11'b01000100100; //Store Word

    4'd2 | 4'd3 | 4'd4 | 4'd5 | 4'd6 | 4'd7 | 4'd8 | 4'd9 | 4'd10 | 4'd11:
    {reg_dst, alu_src, mem_to_reg, reg_w, mem_r, mem_w, beq, bne, alu_op[1:0], j}
    = 11'b10010000000; //ALU연산

    4'd12: {reg_dst, alu_src, mem_to_reg, reg_w, mem_r, mem_w, beq, bne, alu_op[1:0], j}
    = 11'b00000010010; //beq

    4'd13: {reg_dst, alu_src, mem_to_reg, reg_w, mem_r, mem_w, beq, bne, alu_op[1:0], j}
    = 11'b00000001010; //bne

    default: {reg_dst, alu_src, mem_to_reg, reg_w, mem_r, mem_w, beq, bne, alu_op[1:0], j}
    = 11'b00000000001; //jump
    endcase
end
endmodule

chip.v
`include "alu.v"
`include "alucontrol.v"
`include "chipcontrol.v"
`include "gpr.v"
`include "datamemory.v"
`include "instructionmemory.v"
`include "datapath.v"

module chip(
    input clk
);
wire [3:0] opcode;
wire reg_dst, alu_src, mem_to_reg, reg_w, mem_r, mem_w, beq, bne, j;
wire [1:0] alu_op;

chipcontrol chip_connect(
    .opcode(opcode),
    .reg_dst(reg_dst), .alu_src(alu_src), .mem_to_reg(mem_to_reg),
    .reg_w(reg_w), .mem_r(mem_r), .mem_w(mem_w), .beq(beq), .bne(bne), .j(j),
    .alu_op(alu_op)
);

datapath datapath_connect(
    .opcode(opcode), .clk(clk),
    .reg_dst(reg_dst), .alu_src(alu_src), .mem_to_reg(mem_to_reg), .reg_w(reg_w), .mem_r(mem_r), .mem_w(mem_w), .beq(beq), .bne(bne), .j(j),
    .alu_op(alu_op)
);
endmodule

tb.v
`timescale 1ns/1ps
module tb;
reg clk;

initial begin
clk <= 0;
$dumpfile("16bitRISC.vcd");
$dumpvars;
#30 $finish;
end
always begin
#1 clk=~clk;
end

chip DUT(
    .clk(clk)
);
endmodule

16bitRISC.vcd
$date
	Sun Aug 23 23:17:55 2020
$end
$version
	Icarus Verilog
$end
$timescale
	1ps
$end
$scope module tb $end
$var reg 1 ! clk $end
$scope module DUT $end
$var wire 1 ! clk $end
$var wire 1 " reg_w $end
$var wire 1 # reg_dst $end
$var wire 4 $ opcode [3:0] $end
$var wire 1 % mem_w $end
$var wire 1 & mem_to_reg $end
$var wire 1 ' mem_r $end
$var wire 1 ( j $end
$var wire 1 ) bne $end
$var wire 1 * beq $end
$var wire 1 + alu_src $end
$var wire 2 , alu_op [1:0] $end
$scope module chip_connect $end
$var wire 4 - opcode [3:0] $end
$var reg 2 . alu_op [1:0] $end
$var reg 1 + alu_src $end
$var reg 1 * beq $end
$var reg 1 ) bne $end
$var reg 1 ( j $end
$var reg 1 ' mem_r $end
$var reg 1 & mem_to_reg $end
$var reg 1 % mem_w $end
$var reg 1 # reg_dst $end
$var reg 1 " reg_w $end
$upscope $end
$scope module datapath_connect $end
$var wire 2 / alu_op [1:0] $end
$var wire 1 + alu_src $end
$var wire 1 * beq $end
$var wire 1 ) bne $end
$var wire 1 ! clk $end
$var wire 1 ( j $end
$var wire 1 ' mem_r $end
$var wire 1 & mem_to_reg $end
$var wire 1 % mem_w $end
$var wire 1 # reg_dst $end
$var wire 1 " reg_w $end
$var wire 3 0 ws [2:0] $end
$var wire 16 1 wd [15:0] $end
$var wire 3 2 rs2 [2:0] $end
$var wire 3 3 rs1 [2:0] $end
$var wire 16 4 rd2 [15:0] $end
$var wire 16 5 rd1 [15:0] $end
$var wire 16 6 pc_plus2 [15:0] $end
$var wire 16 7 pc_next [15:0] $end
$var wire 16 8 pc_jump [15:0] $end
$var wire 16 9 pc_branch [15:0] $end
$var wire 4 : opcode [3:0] $end
$var wire 16 ; mem_read_data [15:0] $end
$var wire 1 < iszero $end
$var wire 16 = instruction [15:0] $end
$var wire 16 > immext [15:0] $end
$var wire 16 ? b [15:0] $end
$var wire 16 @ alu_out [15:0] $end
$var wire 3 A alu_cnt [2:0] $end
$var reg 16 B pc [15:0] $end
$scope module alu_connect $end
$var wire 16 C b [15:0] $end
$var wire 1 < iszero $end
$var wire 3 D alu_cnt [2:0] $end
$var wire 16 E a [15:0] $end
$var reg 16 F result [15:0] $end
$upscope $end
$scope module alucontrol_connect $end
$var wire 2 G alu_op [1:0] $end
$var wire 4 H opcode [3:0] $end
$var reg 3 I alu_cnt [2:0] $end
$upscope $end
$scope module dm_connect $end
$var wire 1 ! clk $end
$var wire 16 J mem_address [15:0] $end
$var wire 1 ' mem_read_enable $end
$var wire 1 % mem_write_enable $end
$var wire 16 K mem_write_data [15:0] $end
$var wire 16 L mem_read_data [15:0] $end
$upscope $end
$scope module gpr_connect $end
$var wire 1 ! clk $end
$var wire 16 M rd1 [15:0] $end
$var wire 16 N rd2 [15:0] $end
$var wire 3 O rs1 [2:0] $end
$var wire 3 P rs2 [2:0] $end
$var wire 16 Q wd [15:0] $end
$var wire 1 " we $end
$var wire 3 R ws [2:0] $end
$var integer 32 S i [31:0] $end
$upscope $end
$scope module im_connect $end
$var wire 16 T instruction [15:0] $end
$var wire 16 U pc [15:0] $end
$upscope $end
$upscope $end
$upscope $end
$upscope $end
$enddefinitions $end
#0
$dumpvars
b0 U
b10000000000 T
b1000 S
b0 R
b1 Q
b0 P
b10 O
b0 N
b0 M
b1 L
b0 K
b0 J
b0 I
b0 H
b10 G
b0 F
b0 E
b0 D
b0 C
b0 B
b0 A
b0 @
b0 ?
b0 >
b10000000000 =
1<
b1 ;
b0 :
b10 9
b100000000000 8
b10 7
b10 6
b0 5
b0 4
b10 3
b0 2
b1 1
b0 0
b10 /
b10 .
b0 -
b10 ,
1+
0*
0)
0(
1'
1&
0%
b0 $
0#
1"
0!
$end
#1000
b1 0
b1 R
b100 7
b100010000000 8
b1 2
b1 P
b10001000000 =
b10001000000 T
b0 4
b0 K
b0 N
b100 9
b100 6
b10 B
b10 U
1!
#2000
0!
#3000
b10 1
b10 Q
0<
b10 0
b10 R
b0 ;
b0 L
b1 ?
b1 C
b10 @
b10 F
b10 J
1#
0+
0&
0'
b0 ,
b0 .
b0 /
b0 G
b110 7
b10100000 8
b10000 >
b1 5
b1 E
b1 M
b0 3
b0 O
b10 $
b10 -
b10 :
b10 H
b10000001010000 =
b10000001010000 T
b10110 9
b110 6
b100 B
b100 U
b1 4
b1 K
b1 N
1!
#4000
0!
#5000
b1 1
b1 Q
b1 @
b1 F
b1 J
b0 ?
b0 C
0#
1+
0"
1%
b10 ,
b10 .
b10 /
b10 G
b1000 7
b10100000000 8
b0 >
b10 4
b10 K
b10 N
b10 2
b10 P
b1 3
b1 O
b1 $
b1 -
b1 :
b1 H
b1001010000000 =
b1001010000000 T
b1000 9
b1000 6
b110 B
b110 U
1!
#6000
0!
#7000
b10 1
b10 Q
b10 ;
b10 L
b0 0
b0 R
1&
1"
1'
0%
b1010 7
b10000000000 8
b1 4
b1 K
b1 N
b0 2
b0 P
b0 $
b0 -
b0 :
b0 H
b1000000000 =
b1000000000 T
b1010 9
b1010 6
b1000 B
b1000 U
1!
#8000
0!
#9000
b100 1
b100 Q
b0 ;
b0 L
b10 ?
b10 C
b100 @
b100 F
b100 J
0+
0&
0"
0'
b0 ,
b0 .
b0 /
b0 G
1(
b100 7
b100 8
b10 >
b10 5
b10 E
b10 M
b0 3
b0 O
b1101 $
b1101 -
b1101 :
b1101 H
b1101000000000010 =
b1101000000000010 T
b10 4
b10 K
b10 N
b1110 9
b1100 6
b1010 B
b1010 U
1!
#10000
0!
#11000
b11 1
b11 Q
b11 @
b11 F
b11 J
b110 7
b10 0
b10 R
b1 ?
b1 C
1#
1"
0(
b10100000 8
b10000 >
b1 4
b1 K
b1 N
b1 2
b1 P
b10 $
b10 -
b10 :
b10 H
b10000001010000 =
b10000001010000 T
b10110 9
b110 6
b100 B
b100 U
1!
#12000
0!
#13000
b1 1
b1 Q
b0 ?
b0 C
b1 @
b1 F
b1 J
0#
1+
0"
1%
b10 ,
b10 .
b10 /
b10 G
b1000 7
b10100000000 8
b0 >
b11 4
b11 K
b11 N
b10 2
b10 P
b1 5
b1 E
b1 M
b1 3
b1 O
b1 $
b1 -
b1 :
b1 H
b1001010000000 =
b1001010000000 T
b1000 9
b1000 6
b110 B
b110 U
1!
#14000
0!
#15000
b11 1
b11 Q
b11 ;
b11 L
b0 0
b0 R
1&
1"
1'
0%
b1010 7
b10000000000 8
b10 4
b10 K
b10 N
b0 2
b0 P
b0 $
b0 -
b0 :
b0 H
b1000000000 =
b1000000000 T
b1010 9
b1010 6
b1000 B
b1000 U
1!
#16000
0!
#17000
b110 1
b110 Q
b0 ;
b0 L
b11 ?
b11 C
b110 @
b110 F
b110 J
0+
0&
0"
0'
b0 ,
b0 .
b0 /
b0 G
1(
b100 7
b100 8
b10 >
b11 5
b11 E
b11 M
b0 3
b0 O
b1101 $
b1101 -
b1101 :
b1101 H
b1101000000000010 =
b1101000000000010 T
b11 4
b11 K
b11 N
b1110 9
b1100 6
b1010 B
b1010 U
1!
#18000
0!
#19000
b100 1
b100 Q
b100 @
b100 F
b100 J
b110 7
b10 0
b10 R
b1 ?
b1 C
1#
1"
0(
b10100000 8
b10000 >
b1 4
b1 K
b1 N
b1 2
b1 P
b10 $
b10 -
b10 :
b10 H
b10000001010000 =
b10000001010000 T
b10110 9
b110 6
b100 B
b100 U
1!
#20000
0!
#21000
b1 1
b1 Q
b0 ?
b0 C
b1 @
b1 F
b1 J
0#
1+
0"
1%
b10 ,
b10 .
b10 /
b10 G
b1000 7
b10100000000 8
b0 >
b100 4
b100 K
b100 N
b10 2
b10 P
b1 5
b1 E
b1 M
b1 3
b1 O
b1 $
b1 -
b1 :
b1 H
b1001010000000 =
b1001010000000 T
b1000 9
b1000 6
b110 B
b110 U
1!
#22000
0!
#23000
b100 1
b100 Q
b100 ;
b100 L
b0 0
b0 R
1&
1"
1'
0%
b1010 7
b10000000000 8
b11 4
b11 K
b11 N
b0 2
b0 P
b0 $
b0 -
b0 :
b0 H
b1000000000 =
b1000000000 T
b1010 9
b1010 6
b1000 B
b1000 U
1!
#24000
0!
#25000
b1000 1
b1000 Q
b0 ;
b0 L
b100 ?
b100 C
b1000 @
b1000 F
b1000 J
0+
0&
0"
0'
b0 ,
b0 .
b0 /
b0 G
1(
b100 7
b100 8
b10 >
b100 5
b100 E
b100 M
b0 3
b0 O
b1101 $
b1101 -
b1101 :
b1101 H
b1101000000000010 =
b1101000000000010 T
b100 4
b100 K
b100 N
b1110 9
b1100 6
b1010 B
b1010 U
1!
#26000
0!
#27000
b101 1
b101 Q
b101 @
b101 F
b101 J
b110 7
b10 0
b10 R
b1 ?
b1 C
1#
1"
0(
b10100000 8
b10000 >
b1 4
b1 K
b1 N
b1 2
b1 P
b10 $
b10 -
b10 :
b10 H
b10000001010000 =
b10000001010000 T
b10110 9
b110 6
b100 B
b100 U
1!
#28000
0!
#29000
b1 1
b1 Q
b0 ?
b0 C
b1 @
b1 F
b1 J
0#
1+
0"
1%
b10 ,
b10 .
b10 /
b10 G
b1000 7
b10100000000 8
b0 >
b101 4
b101 K
b101 N
b10 2
b10 P
b1 5
b1 E
b1 M
b1 3
b1 O
b1 $
b1 -
b1 :
b1 H
b1001010000000 =
b1001010000000 T
b1000 9
b1000 6
b110 B
b110 U
1!
